{
  "schema_version": 1,
  "releases": [
    {
      "version": "2.1.10",
      "kms_release_tag": "2.1.10",
      "kms_policy_path": "policies/mero-kms-phala/2.1.10.json",
      "kms_policy_sha256": "3f4fa746844408507fcd202b8a7e7e939e4f8ab3e5baa7f9cb9447717254a964",
      "merod_release_tag": "locked-image-v2.1.10",
      "merod_policy_path": "policies/merod-locked-image/2.1.10.json",
      "merod_policy_sha256": "17c323d395b24890800507d31ea3ee7c596d03d700c9308b1749aafab00159fa",
      "updated_at": "2026-03-05T16:07:19Z"
    },
    {
      "version": "2.1.9",
      "kms_release_tag": "2.1.9",
      "kms_policy_path": "policies/mero-kms-phala/2.1.9.json",
      "kms_policy_sha256": "76109fad3327731b316356006640aa441909ab51cdd438a8ce069d0ab848f487",
      "merod_release_tag": "2.1.9",
      "merod_policy_path": "policies/merod-locked-image/2.1.9.json",
      "merod_policy_sha256": "4a79f5d8e4f1b301ff92f0712bc3225b01cf131ca1e5c57766db22596e023d51",
      "updated_at": "2026-03-05T15:49:42Z"
    },
    {
      "version": "2.1.8",
      "kms_release_tag": "2.1.8",
      "kms_policy_path": "policies/mero-kms-phala/2.1.8.json",
      "kms_policy_sha256": "0fc9762074eb7f1d3f11816a1e0f4fb05eeb2e8bedd31530acbbcd7e693ce3db",
      "merod_release_tag": "2.1.8",
      "merod_policy_path": "policies/merod-locked-image/2.1.8.json",
      "merod_policy_sha256": "5f713ceff89416ea23ceac708fa92aef5d42285cd349880e3dcbbca291835f45",
      "updated_at": "2026-03-05T15:21:42Z"
    },
    {
      "version": "2.1.7",
      "kms_release_tag": "2.1.7",
      "kms_policy_path": "policies/mero-kms-phala/2.1.7.json",
      "kms_policy_sha256": "5fc303bd9142a5fc41e7725685e9dc5af1279f81973d034d7155cf09b87ef04b",
      "merod_release_tag": "2.1.7",
      "merod_policy_path": "policies/merod-locked-image/2.1.7.json",
      "merod_policy_sha256": "bca633717af7412afeb0ffcd13743899f48eb254b3100a62e80c40d7a1261139",
      "updated_at": "2026-03-05T15:04:37Z"
    },
    {
      "version": "2.1.6",
      "kms_release_tag": "2.1.6",
      "kms_policy_path": "policies/mero-kms-phala/2.1.6.json",
      "kms_policy_sha256": "0ffd99154654c4fc379038b9f6d622cc0e537c20c1b3930233c351868dc66a0c",
      "merod_release_tag": "2.1.6",
      "merod_policy_path": "policies/merod-locked-image/2.1.6.json",
      "merod_policy_sha256": "a5e0278b4487a9a8a35dcdeb86d9ca10dac4af264879c95419bf1549228126ff",
      "updated_at": "2026-03-05T12:04:25Z"
    },
    {
      "version": "2.1.5",
      "kms_release_tag": "2.1.5",
      "kms_policy_path": "policies/mero-kms-phala/2.1.5.json",
      "kms_policy_sha256": "9ce1a292a0a42b925ba22178cd305bf92f91328e3296478d2dbd20f4f045a34e",
      "merod_release_tag": "2.1.5",
      "merod_policy_path": "policies/merod-locked-image/2.1.5.json",
      "merod_policy_sha256": "be85fe9f307a2b6981a6c097d0d126195c37bb97da4d67145b4d1c41ea12d576",
      "updated_at": "2026-03-05T11:51:14Z"
    },
    {
      "version": "2.1.4",
      "kms_release_tag": "2.1.4",
      "kms_policy_path": "policies/mero-kms-phala/2.1.4.json",
      "kms_policy_sha256": "4a79868b9fa0fe46ba1b80ad56259bffc8fac58fb5cdbadda1924c9db6b9cf2a",
      "merod_release_tag": "2.1.4",
      "merod_policy_path": "policies/merod-locked-image/2.1.4.json",
      "merod_policy_sha256": "3a58d314e59b618d3c72a1cbe30e1ac04706ad8eaedc1d49c79a4d78e9be15e5",
      "updated_at": "2026-03-04T23:01:55Z"
    }
  ]
}
